processador_imagens/__init__.py
processador_imagens/processamento/__init__.py
processador_imagens/processamento/combinacao.py
processador_imagens/processamento/transformacao.py
processador_imagens/utils/__init__.py
processador_imagens/utils/io.py
processador_imagens/utils/plot.py
processador_imagens-0.0.1.dist-info/METADATA
processador_imagens-0.0.1.dist-info/WHEEL
processador_imagens-0.0.1.dist-info/top_level.txt
processador_imagens-0.0.1.dist-info/RECORD
