Metadata-Version: 2.1
Name: processador-imagens
Version: 0.0.1
Summary: Pacote de processamento de imagens
Home-page: https://github.com/guilhermercarv/package-template
Author: Guilherme
Author-email: guilhermecarvalho056@gmail.com
License: UNKNOWN
Platform: UNKNOWN
Requires-Python: >=3.8
Requires-Dist: matplotlib
Requires-Dist: numpy
Requires-Dist: scikit-image (>=0.16.1)
